src/__init__.py
src/exception.py
src/logger.py
src/utils.py
src/components/__init__.py
src/components/data_ingestion.py
src/components/data_transformation.py
src/components/model_trainer.py
src/pipeline/__init__.py
src/pipeline/predict_pipeline.py
src/pipeline/train_pipeline.py
Academic_Forecasting_System-0.0.1.dist-info/METADATA
Academic_Forecasting_System-0.0.1.dist-info/WHEEL
Academic_Forecasting_System-0.0.1.dist-info/top_level.txt
Academic_Forecasting_System-0.0.1.dist-info/RECORD
