Metadata-Version: 2.1
Name: Academic-Forecasting-System
Version: 0.0.1
Author: Karthik G Kumar
Author-email: karthikgkumar2002@gmail.com
Requires-Dist: pandas
Requires-Dist: numpy
Requires-Dist: seaborn
Requires-Dist: matplotlib
Requires-Dist: scikit-learn
Requires-Dist: catboost
Requires-Dist: xgboost
Requires-Dist: dill
Requires-Dist: flask
